LICENSE
MANIFEST.in
README.md
setup.cfg
setup.py
tap_harvest_forecast/__init__.py
tap_harvest_forecast.egg-info/PKG-INFO
tap_harvest_forecast.egg-info/SOURCES.txt
tap_harvest_forecast.egg-info/dependency_links.txt
tap_harvest_forecast.egg-info/entry_points.txt
tap_harvest_forecast.egg-info/requires.txt
tap_harvest_forecast.egg-info/top_level.txt
tap_harvest_forecast/schemas/assignments.json
tap_harvest_forecast/schemas/clients.json
tap_harvest_forecast/schemas/milestones.json
tap_harvest_forecast/schemas/people.json
tap_harvest_forecast/schemas/placeholders.json
tap_harvest_forecast/schemas/projects.json
tap_harvest_forecast/schemas/roles.json