Metadata-Version: 1.1
Name: tap-harvest-forecast
Version: 1.1.0
Summary: Singer.io tap for extracting data from the Harvest Forecast api
Home-page: https://github.com/singer-io/tap-harvest-forecast
Author: Robert Benjamin
Author-email: UNKNOWN
License: UNKNOWN
Platform: UNKNOWN
Classifier: Programming Language :: Python :: 3 :: Only
